aproxy/__init__.py
aproxy/__main__.py
aproxy/proxy.py
aproxy/proxy_config.py
aproxy/util.py
aproxy/version.py
aproxy/providers/__init__.py
aproxy/providers/kube_util.py
aproxy/providers/kubernetes.py
aproxy/providers/provider_config.py
aproxy/providers/ssh.py
aproxy/providers/staging_error.py
aproxy/providers/staging_pod.py
aproxy-1.9.2.dist-info/LICENSE
aproxy-1.9.2.dist-info/METADATA
aproxy-1.9.2.dist-info/WHEEL
aproxy-1.9.2.dist-info/entry_points.txt
aproxy-1.9.2.dist-info/top_level.txt
aproxy-1.9.2.dist-info/RECORD
