Metadata-Version: 2.1
Name: aproxy
Version: 1.9.2
Summary: Simple tool that lets you run multiple proxies simultaneously
Home-page: https://github.com/frodehus/aproxy
Author: Frode Hus
Author-email: frode.hus@outlook.com
License: UNKNOWN
Platform: UNKNOWN
Classifier: Programming Language :: Python :: 3
Classifier: License :: OSI Approved :: MIT License
Requires-Python: >=3.6
Requires-Dist: hexdump
Requires-Dist: colorama
Requires-Dist: knack
Requires-Dist: kubernetes
Requires-Dist: paramiko
Requires-Dist: progress
